odoo/addons/account_reporting_volume/README.rst
odoo/addons/account_reporting_volume/__init__.py
odoo/addons/account_reporting_volume/__manifest__.py
odoo/addons/account_reporting_volume/i18n/account_reporting_volume.pot
odoo/addons/account_reporting_volume/i18n/es.po
odoo/addons/account_reporting_volume/i18n/it.po
odoo/addons/account_reporting_volume/models/__init__.py
odoo/addons/account_reporting_volume/models/account_invoice_report.py
odoo/addons/account_reporting_volume/readme/CONTRIBUTORS.md
odoo/addons/account_reporting_volume/readme/DESCRIPTION.md
odoo/addons/account_reporting_volume/readme/USAGE.md
odoo/addons/account_reporting_volume/static/description/icon.png
odoo/addons/account_reporting_volume/static/description/index.html
odoo_addon_account_reporting_volume-18.0.1.0.0.2.dist-info/METADATA
odoo_addon_account_reporting_volume-18.0.1.0.0.2.dist-info/WHEEL
odoo_addon_account_reporting_volume-18.0.1.0.0.2.dist-info/top_level.txt
odoo_addon_account_reporting_volume-18.0.1.0.0.2.dist-info/RECORD
